{
  "classes": [
    "apartment",
    "church",
    "garage",
    "house",
    "industrial",
    "officebuilding",
    "retail",
    "roof"
  ],
  "class_labels": [
    "Apartment",
    "Church",
    "Garage",
    "House",
    "Industrial",
    "Office Bldg",
    "Retail",
    "Roof"
  ],
  "img_size": 224,
  "num_classes": 8,
  "winner_model": "EfficientNetB0 (fine-tuned)",
  "test_accuracy": 0.6157,
  "all_results": {
    "ResNet50 (frozen)": 0.5723,
    "EfficientNetB0 (frozen)": 0.5892,
    "MobileNetV2 (frozen)": 0.5517,
    "EfficientNetB0 (fine-tuned)": 0.6157
  },
  "timestamp": "20260221_000416",
  "train_images": 13547,
  "val_images": 2903,
  "test_images": 2904
}